markdown_include/__init__.py
markdown_include/include.py
markdown_include_annotated-1.0.2.dist-info/licenses/LICENSE.txt
markdown_include_annotated-1.0.2.dist-info/METADATA
markdown_include_annotated-1.0.2.dist-info/WHEEL
markdown_include_annotated-1.0.2.dist-info/top_level.txt
markdown_include_annotated-1.0.2.dist-info/RECORD
